{
	"file_path": "C:\\Users\\Adam\\AppData\\Local\\Packages\\Microsoft.MinecraftUWP_8wekyb3d8bbwe\\LocalState\\games\\com.mojang\\development_behavior_packs\\Spacon/animation_controllers/jetpack.json",
	"file_type": "animation_controller",
	"format_version": 1,
	"file_uuid": "1aa3e5fc_e1d9_4e83_8ac0_1986ffcb57fd",
	"file_version": 2,
	"cache_content": {
		"open": true,
		"comment": "",
		"data": "",
		"key": "global",
		"type": "object",
		"meta": {},
		"children": [
			{
				"open": false,
				"comment": "",
				"data": "1.10.0",
				"key": "format_version",
				"type": "string",
				"meta": {},
				"children": []
			},
			{
				"open": true,
				"comment": "",
				"data": "",
				"key": "animation_controllers",
				"type": "object",
				"meta": {},
				"children": [
					{
						"open": true,
						"comment": "",
						"data": "",
						"key": "controller.animation.jetpack",
						"type": "object",
						"meta": {},
						"children": [
							{
								"open": false,
								"comment": "",
								"data": "",
								"key": "states",
								"type": "object",
								"meta": {},
								"children": [
									{
										"open": false,
										"comment": "",
										"data": "",
										"key": "default",
										"type": "object",
										"meta": {},
										"children": [
											{
												"open": false,
												"comment": "",
												"data": "",
												"key": "on_entry",
												"type": "array",
												"meta": {},
												"children": [
													{
														"open": false,
														"comment": "",
														"data": "/effect @s levitation 0",
														"key": "0",
														"type": "string",
														"meta": {},
														"children": []
													}
												]
											},
											{
												"open": false,
												"comment": "",
												"data": "",
												"key": "transitions",
												"type": "array",
												"meta": {},
												"children": [
													{
														"open": false,
														"comment": "",
														"data": "",
														"key": "0",
														"type": "object",
														"meta": {},
														"children": [
															{
																"open": false,
																"comment": "",
																"data": "query.is_saddled",
																"key": "hover",
																"type": "string",
																"meta": {},
																"children": []
															}
														]
													}
												]
											}
										]
									},
									{
										"open": false,
										"comment": "",
										"data": "",
										"key": "hover",
										"type": "object",
										"meta": {},
										"children": [
											{
												"open": false,
												"comment": "",
												"data": "",
												"key": "on_entry",
												"type": "array",
												"meta": {},
												"children": [
													{
														"open": false,
														"comment": "",
														"data": "/effect @s levitation 0",
														"key": "0",
														"type": "string",
														"meta": {},
														"children": []
													},
													{
														"open": false,
														"comment": "",
														"data": "@s spacon:jetpack_hover",
														"key": "1",
														"type": "string",
														"meta": {},
														"children": []
													}
												]
											},
											{
												"open": false,
												"comment": "",
												"data": "",
												"key": "transitions",
												"type": "array",
												"meta": {},
												"children": [
													{
														"open": false,
														"comment": "",
														"data": "",
														"key": "0",
														"type": "object",
														"meta": {},
														"children": [
															{
																"open": false,
																"comment": "",
																"data": "query.is_jumping",
																"key": "rise",
																"type": "string",
																"meta": {},
																"children": []
															}
														]
													},
													{
														"open": false,
														"comment": "",
														"data": "",
														"key": "1",
														"type": "object",
														"meta": {},
														"children": [
															{
																"open": false,
																"comment": "",
																"data": "query.is_sneaking",
																"key": "fall",
																"type": "string",
																"meta": {},
																"children": []
															}
														]
													},
													{
														"open": false,
														"comment": "",
														"data": "",
														"key": "2",
														"type": "object",
														"meta": {},
														"children": [
															{
																"open": false,
																"comment": "",
																"data": "!query.is_saddled",
																"key": "default",
																"type": "string",
																"meta": {},
																"children": []
															}
														]
													}
												]
											}
										]
									},
									{
										"open": false,
										"comment": "",
										"data": "",
										"key": "rise",
										"type": "object",
										"meta": {},
										"children": [
											{
												"open": false,
												"comment": "",
												"data": "",
												"key": "animations",
												"type": "array",
												"meta": {},
												"children": [
													{
														"open": false,
														"comment": "",
														"data": "",
														"key": "0",
														"type": "object",
														"meta": {},
														"children": [
															{
																"open": false,
																"comment": "",
																"data": "(1.0)",
																"key": "jetpack_rise",
																"type": "string",
																"meta": {},
																"children": []
															}
														]
													}
												]
											},
											{
												"open": false,
												"comment": "",
												"data": "",
												"key": "transitions",
												"type": "array",
												"meta": {},
												"children": [
													{
														"open": false,
														"comment": "",
														"data": "",
														"key": "0",
														"type": "object",
														"meta": {},
														"children": [
															{
																"open": false,
																"comment": "",
																"data": "!query.is_jumping",
																"key": "hover",
																"type": "string",
																"meta": {},
																"children": []
															}
														]
													}
												]
											},
											{
												"open": false,
												"comment": "",
												"data": "",
												"key": "on_exit",
												"type": "array",
												"meta": {},
												"children": [
													{
														"open": false,
														"comment": "",
														"data": "/effect @s levitation 0",
														"key": "0",
														"type": "string",
														"meta": {},
														"children": []
													}
												]
											}
										]
									},
									{
										"open": false,
										"comment": "",
										"data": "",
										"key": "fall",
										"type": "object",
										"meta": {},
										"children": [
											{
												"open": false,
												"comment": "",
												"data": "",
												"key": "on_entry",
												"type": "array",
												"meta": {},
												"children": [
													{
														"open": false,
														"comment": "",
														"data": "/effect @s levitation 0",
														"key": "0",
														"type": "string",
														"meta": {},
														"children": []
													},
													{
														"open": false,
														"comment": "",
														"data": "@s spacon:jetpack_fall",
														"key": "1",
														"type": "string",
														"meta": {},
														"children": []
													}
												]
											},
											{
												"open": false,
												"comment": "",
												"data": "",
												"key": "transitions",
												"type": "array",
												"meta": {},
												"children": [
													{
														"open": false,
														"comment": "",
														"data": "",
														"key": "0",
														"type": "object",
														"meta": {},
														"children": [
															{
																"open": false,
																"comment": "",
																"data": "!query.is_sneaking",
																"key": "hover",
																"type": "string",
																"meta": {},
																"children": []
															}
														]
													}
												]
											}
										]
									}
								]
							}
						]
					},
					{
						"open": true,
						"comment": "",
						"data": "",
						"key": "controller.animation.jetpack.activator",
						"type": "object",
						"meta": {},
						"children": [
							{
								"open": false,
								"comment": "",
								"data": "",
								"key": "states",
								"type": "object",
								"meta": {},
								"children": [
									{
										"open": false,
										"comment": "",
										"data": "",
										"key": "default",
										"type": "object",
										"meta": {},
										"children": [
											{
												"open": false,
												"comment": "",
												"data": "",
												"key": "transitions",
												"type": "array",
												"meta": {},
												"children": [
													{
														"open": false,
														"comment": "",
														"data": "",
														"key": "0",
														"type": "object",
														"meta": {},
														"children": [
															{
																"open": false,
																"comment": "",
																"data": "query.armor_texture_slot(1) == 3 && query.is_jumping",
																"key": "jump_a",
																"type": "string",
																"meta": {},
																"children": []
															}
														]
													},
													{
														"open": false,
														"comment": "",
														"data": "",
														"key": "1",
														"type": "object",
														"meta": {},
														"children": [
															{
																"open": false,
																"comment": "",
																"data": "query.armor_texture_slot(1) != 3",
																"key": "deactivate",
																"type": "string",
																"meta": {},
																"children": []
															}
														]
													}
												]
											}
										]
									},
									{
										"open": false,
										"comment": "",
										"data": "",
										"key": "jump_a",
										"type": "object",
										"meta": {},
										"children": [
											{
												"open": false,
												"comment": "",
												"data": "",
												"key": "transitions",
												"type": "array",
												"meta": {},
												"children": [
													{
														"open": false,
														"comment": "",
														"data": "",
														"key": "0",
														"type": "object",
														"meta": {},
														"children": [
															{
																"open": false,
																"comment": "",
																"data": "!query.is_jumping",
																"key": "jump_b",
																"type": "string",
																"meta": {},
																"children": []
															}
														]
													},
													{
														"open": false,
														"comment": "",
														"data": "",
														"key": "1",
														"type": "object",
														"meta": {},
														"children": [
															{
																"open": false,
																"comment": "",
																"data": "query.any_animation_finished",
																"key": "default",
																"type": "string",
																"meta": {},
																"children": []
															}
														]
													}
												]
											},
											{
												"open": false,
												"comment": "",
												"data": "",
												"key": "animations",
												"type": "array",
												"meta": {},
												"children": [
													{
														"open": false,
														"comment": "",
														"data": "",
														"key": "0",
														"type": "object",
														"meta": {},
														"children": [
															{
																"open": false,
																"comment": "",
																"data": "(1.0)",
																"key": "jetpack_cd",
																"type": "string",
																"meta": {},
																"children": []
															}
														]
													}
												]
											}
										]
									},
									{
										"open": false,
										"comment": "",
										"data": "",
										"key": "jump_b",
										"type": "object",
										"meta": {},
										"children": [
											{
												"open": false,
												"comment": "",
												"data": "",
												"key": "transitions",
												"type": "array",
												"meta": {},
												"children": [
													{
														"open": false,
														"comment": "",
														"data": "",
														"key": "0",
														"type": "object",
														"meta": {},
														"children": [
															{
																"open": false,
																"comment": "",
																"data": "query.is_jumping",
																"key": "double_jump",
																"type": "string",
																"meta": {},
																"children": []
															}
														]
													},
													{
														"open": false,
														"comment": "",
														"data": "",
														"key": "1",
														"type": "object",
														"meta": {},
														"children": [
															{
																"open": false,
																"comment": "",
																"data": "query.any_animation_finished",
																"key": "default",
																"type": "string",
																"meta": {},
																"children": []
															}
														]
													}
												]
											},
											{
												"open": false,
												"comment": "",
												"data": "",
												"key": "animations",
												"type": "array",
												"meta": {},
												"children": [
													{
														"open": false,
														"comment": "",
														"data": "",
														"key": "0",
														"type": "object",
														"meta": {},
														"children": [
															{
																"open": false,
																"comment": "",
																"data": "(1.0)",
																"key": "jetpack_cd",
																"type": "string",
																"meta": {},
																"children": []
															}
														]
													}
												]
											}
										]
									},
									{
										"open": false,
										"comment": "",
										"data": "",
										"key": "double_jump",
										"type": "object",
										"meta": {},
										"children": [
											{
												"open": false,
												"comment": "",
												"data": "",
												"key": "transitions",
												"type": "array",
												"meta": {},
												"children": [
													{
														"open": false,
														"comment": "",
														"data": "",
														"key": "0",
														"type": "object",
														"meta": {},
														"children": [
															{
																"open": false,
																"comment": "",
																"data": "query.is_saddled",
																"key": "deactivate",
																"type": "string",
																"meta": {},
																"children": []
															}
														]
													},
													{
														"open": false,
														"comment": "",
														"data": "",
														"key": "1",
														"type": "object",
														"meta": {},
														"children": [
															{
																"open": false,
																"comment": "",
																"data": "!query.is_saddled",
																"key": "activate",
																"type": "string",
																"meta": {},
																"children": []
															}
														]
													}
												]
											}
										]
									},
									{
										"open": false,
										"comment": "",
										"data": "",
										"key": "deactivate",
										"type": "object",
										"meta": {},
										"children": [
											{
												"open": false,
												"comment": "",
												"data": "",
												"key": "transitions",
												"type": "array",
												"meta": {},
												"children": [
													{
														"open": false,
														"comment": "",
														"data": "",
														"key": "0",
														"type": "object",
														"meta": {},
														"children": [
															{
																"open": false,
																"comment": "",
																"data": "(1.0)",
																"key": "default",
																"type": "string",
																"meta": {},
																"children": []
															}
														]
													}
												]
											},
											{
												"open": false,
												"comment": "",
												"data": "",
												"key": "on_entry",
												"type": "array",
												"meta": {},
												"children": [
													{
														"open": false,
														"comment": "",
														"data": "@s spacon:deactivate_jetpack",
														"key": "0",
														"type": "string",
														"meta": {},
														"children": []
													}
												]
											}
										]
									},
									{
										"open": false,
										"comment": "",
										"data": "",
										"key": "activate",
										"type": "object",
										"meta": {},
										"children": [
											{
												"open": false,
												"comment": "",
												"data": "",
												"key": "transitions",
												"type": "array",
												"meta": {},
												"children": [
													{
														"open": false,
														"comment": "",
														"data": "",
														"key": "0",
														"type": "object",
														"meta": {},
														"children": [
															{
																"open": false,
																"comment": "",
																"data": "(1.0)",
																"key": "default",
																"type": "string",
																"meta": {},
																"children": []
															}
														]
													}
												]
											},
											{
												"open": false,
												"comment": "",
												"data": "",
												"key": "on_entry",
												"type": "array",
												"meta": {},
												"children": [
													{
														"open": false,
														"comment": "",
														"data": "@s spacon:activate_jetpack",
														"key": "0",
														"type": "string",
														"meta": {},
														"children": []
													},
													{
														"open": false,
														"comment": "",
														"data": "/effect @s levitation 1 5 true",
														"key": "1",
														"type": "string",
														"meta": {},
														"children": []
													}
												]
											}
										]
									}
								]
							}
						]
					}
				]
			}
		]
	}
}